trading_models/__init__.py
trading_models/learn.py
trading_models/sanity_check.py
trading_models/simple_models.py
trading_models/stat.py
trading_models/utils.py
trading_models-0.3.7.dist-info/METADATA
trading_models-0.3.7.dist-info/WHEEL
trading_models-0.3.7.dist-info/top_level.txt
trading_models-0.3.7.dist-info/RECORD
