Metadata-Version: 2.4
Name: trading-models
Version: 0.3.7
Summary: MLP, CNN, Transformer models for time-series trading predictions.
Home-page: https://github.com/SerenaTradingResearch/trading-models
Author: Ricky Ding
Author-email: e0134117@u.nus.edu
License: MIT
Keywords: trading models,neural networks,time-series,MLP,CNN,Transformer
Classifier: Programming Language :: Python :: 3
Classifier: Intended Audience :: Financial and Insurance Industry
Classifier: License :: OSI Approved :: MIT License
Requires-Python: >=3.8
Requires-Dist: torch
Requires-Dist: matplotlib
Requires-Dist: numpy
Requires-Dist: Pillow
Requires-Dist: pandas
Requires-Dist: seaborn
Requires-Dist: scikit-learn
Requires-Dist: statsmodels
Dynamic: author
Dynamic: author-email
Dynamic: classifier
Dynamic: description
Dynamic: description-content-type
Dynamic: home-page
Dynamic: keywords
Dynamic: license
Dynamic: requires-dist
Dynamic: requires-python
Dynamic: summary
